{
"table":[
  {
  [
    {
        "SUBJ": "ART",
        "CRS": "1120",
        "CRN": "4101",
        "TITLE": "2D Surface(formerly 2D Design)",
        "CREDITS": "3",
        "DAYS": "TR",
        "COMPLETED": false,
        "EMPHASIS": "0"
    },
    {
        "SUBJ": "ART",
        "CRS": "1140",
        "CRN": "4736",
        "TITLE": "4D Time",
        "CREDITS": "3",
        "DAYS": "MW",
        "COMPLETED": false,
        "EMPHASIS": "0"
    },
    {
        "SUBJ": "ART",
        "CRS": "2400",
        "CRN": "4955",
        "TITLE": "Intro to Graphic Design",
        "CREDITS": "3",
        "DAYS": "MW",
        "COMPLETED": false,
        "EMPHASIS": "0"
    },
    {
        "SUBJ": "BIOL",
        "CRS": "2030",
        "CRN": "5077",
        "TITLE": "Introductory Genetics",
        "CREDITS": "4",
        "DAYS": "MTW",
        "COMPLETED": false,
        "EMPHASIS": "e"
    },
    {
        "SUBJ": "BIOL",
        "CRS": "2035",
        "CRN": "4234",
        "TITLE": "Introductory Genetics Lab  LB",
        "CREDITS": "1",
        "DAYS": "F",
        "COMPLETED": false,
        "EMPHASIS": "e"
    },
    {
        "SUBJ": "BIOL",
        "CRS": "2060",
        "CRN": "4236",
        "TITLE": "Introductory Microbiology  LS",
        "CREDITS": "3",
        "DAYS": "MTW",
        "COMPLETED": false,
        "EMPHASIS": "e"
    },
    {
        "SUBJ": "BIOL",
        "CRS": "2065",
        "CRN": "4237",
        "TITLE": "Intro Microbiology Lab  LB",
        "CREDITS": "1",
        "DAYS": "T",
        "COMPLETED": false,
        "EMPHASIS": "e"
    },
    {
        "SUBJ": "BUS",
        "CRS": "1600",
        "CRN": "4517",
        "TITLE": "Entrepreneurship Seminars",
        "CREDITS": "1",
        "DAYS": "W",
        "COMPLETED": false,
        "EMPHASIS": "1"
    },
    {
        "SUBJ": "BUS",
        "CRS": "2222",
        "CRN": "5156",
        "TITLE": "Entrepreneurship",
        "CREDITS": "3",
        "DAYS": "MWF",
        "COMPLETED": false,
        "EMPHASIS": "1"
    },
    {
        "SUBJ": "BUS",
        "CRS": "2650",
        "CRN": "5158",
        "TITLE": "Management Prin/Entrepreneurs",
        "CREDITS": "3",
        "DAYS": "TR",
        "COMPLETED": false,
        "EMPHASIS": "1"
    },
    {
        "SUBJ": "CHEM",
        "CRS": "1210",
        "CRN": "4117",
        "TITLE": "Principles of Chemistry I PS",
        "CREDITS": "4",
        "DAYS": "MTWF",
        "COMPLETED": false,
        "EMPHASIS": "e"
    },
    {
        "SUBJ": "CHEM",
        "CRS": "1215",
        "CRN": "4215",
        "TITLE": "Prin of Chemistry Lab I  LB",
        "CREDITS": "1",
        "DAYS": "R",
        "COMPLETED": false,
        "EMPHASIS": "e"
    },
    {
        "SUBJ": "COMM",
        "CRS": "2110",
        "CRN": "4661",
        "TITLE": "Interpersonal Comm  OC",
        "CREDITS": "3",
        "DAYS": "TR",
        "COMPLETED": false,
        "EMPHASIS": null
    },
    {
        "SUBJ": "CS",
        "CRS": "1410",
        "CRN": "4756",
        "TITLE": "Object-Oriented Programming",
        "CREDITS": "3",
        "DAYS": "MWF",
        "COMPLETED": false,
        "EMPHASIS": null
    },
    {
        "SUBJ": "CS",
        "CRS": "1415",
        "CRN": "4766",
        "TITLE": "Object-Oriented Program Lab",
        "CREDITS": "1",
        "DAYS": "T",
        "COMPLETED": false,
        "EMPHASIS": null
    },
    {
        "SUBJ": "CS",
        "CRS": "1430",
        "CRN": "4766",
        "TITLE": "User Experience Design",
        "CREDITS": "1",
        "DAYS": "T",
        "COMPLETED": false,
        "EMPHASIS": null
    },
    {
        "SUBJ": "CS",
        "CRS": "1810",
        "CRN": "4962",
        "TITLE": "Web Development I",
        "CREDITS": "3",
        "DAYS": "TR",
        "COMPLETED": false,
        "EMPHASIS": null
    },
    {
        "SUBJ": "CS",
        "CRS": "2420",
        "CRN": "4027",
        "TITLE": "Data Structures & Algorithms",
        "CREDITS": "3",
        "DAYS": "MWF",
        "COMPLETED": false,
        "EMPHASIS": null
    },
    {
        "SUBJ": "CS",
        "CRS": "2450",
        "CRN": "4816",
        "TITLE": "Intro to Software Engineering",
        "CREDITS": "3",
        "DAYS": "MWF",
        "COMPLETED": false,
        "EMPHASIS": null
    },
    {
        "SUBJ": "CS",
        "CRS": "2700",
        "CRN": "5103",
        "TITLE": "Digital Circuits",
        "CREDITS": "3",
        "DAYS": "MWF",
        "COMPLETED": false,
        "EMPHASIS": null
    },
    {
        "SUBJ": "CS",
        "CRS": "2810",
        "CRN": "5009",
        "TITLE": "Computer Organiz/Architecture",
        "CREDITS": "3",
        "DAYS": "MWF",
        "COMPLETED": false,
        "EMPHASIS": null
    },
    {
        "SUBJ": "ENGL",
        "CRS": "3260",
        "CRN": "4816",
        "TITLE": "Technical Writing",
        "CREDITS": "3",
        "DAYS": "MWF",
        "COMPLETED": false,
        "EMPHASIS": null
    },
    {
        "SUBJ": "MATH",
        "CRS": "1210",
        "CRN": "4313",
        "TITLE": "Calculus I",
        "CREDITS": "5",
        "DAYS": "MTWRF",
        "COMPLETED": false,
        "EMPHASIS": null
    },
    {
        "SUBJ": "MATH",
        "CRS": "1220",
        "CRN": "4261",
        "TITLE": "Calculus II",
        "CREDITS": "4",
        "DAYS": "MTWF",
        "COMPLETED": false,
        "EMPHASIS": null
    },
    {
        "SUBJ": "MATH",
        "CRS": "2210",
        "CRN": "4261",
        "TITLE": "Calculus III",
        "CREDITS": "4",
        "DAYS": "MTWF",
        "COMPLETED": false,
        "EMPHASIS": "e"
    },
    {
        "SUBJ": "MATH",
        "CRS": "2270",
        "CRN": "5945",
        "TITLE": "Linear Algebra",
        "CREDITS": "3",
        "DAYS": "MWF",
        "COMPLETED": false,
        "EMPHASIS": null
    },
    {
        "SUBJ": "MATH",
        "CRS": "3040",
        "CRN": "4874",
        "TITLE": "Stats for Scientists & Engr",
        "CREDITS": "3",
        "DAYS": "MWF",
        "COMPLETED": false,
        "EMPHASIS": null
    },
    {
        "SUBJ": "MATH",
        "CRS": "3080",
        "CRN": "6041",
        "TITLE": "Applied Linear Regression",
        "CREDITS": "3",
        "DAYS": "MWF",
        "COMPLETED": false,
        "EMPHASIS": "2"
    },
    {
        "SUBJ": "MATH",
        "CRS": "3310",
        "CRN": "4873",
        "TITLE": "Discrete Mathematics",
        "CREDITS": "3",
        "DAYS": "MWF",
        "COMPLETED": false,
        "EMPHASIS": null
    },
    {
        "SUBJ": "MATH",
        "CRS": "3280",
        "CRN": "4873",
        "TITLE": "Data Mining",
        "CREDITS": "3",
        "DAYS": "MWF",
        "COMPLETED": false,
        "EMPHASIS": "2"
    },
    {
        "SUBJ": "MATH",
        "CRS": "3480",
        "CRN": "4873",
        "TITLE": "Theory of Machine Learning",
        "CREDITS": "3",
        "DAYS": "MWF",
        "COMPLETED": false,
        "EMPHASIS": "2"
    },
    {
        "SUBJ": "PHYS",
        "CRS": "2010",
        "CRN": "4139",
        "TITLE": "College Physics I",
        "CREDITS": "4",
        "DAYS": "MWF",
        "COMPLETED": false,
        "EMPHASIS": null
    },
    {
        "SUBJ": "PHYS",
        "CRS": "2015",
        "CRN": "4140",
        "TITLE": "College Physics I Lab",
        "CREDITS": "1",
        "DAYS": "R",
        "COMPLETED": false,
        "EMPHASIS": null
    },
    {
        "SUBJ": "PHYS",
        "CRS": "2220",
        "CRN": "5094",
        "TITLE": "Physics:Scientist/Engineers II",
        "CREDITS": "4",
        "DAYS": "MTWF",
        "COMPLETED": false,
        "EMPHASIS": null
    },
    {
        "SUBJ": "PHYS",
        "CRS": "2225",
        "CRN": "5095",
        "TITLE": "Phys:Scientist/Engineer II Lab",
        "CREDITS": "1",
        "DAYS": "R",
        "COMPLETED": false,
        "EMPHASIS": null
    },
    {
        "SUBJ": "PHYS",
        "CRS": "2710",
        "CRN": "5095",
        "TITLE": "Modern Physics",
        "CREDITS": "3",
        "DAYS": "R",
        "COMPLETED": false,
        "EMPHASIS": "e"
    },
    {
        "SUBJ": "SE",
        "CRS": "3140",
        "CRN": "5106",
        "TITLE": "Ethics and Personal Software",
        "CREDITS": "3",
        "DAYS": "MWF",
        "COMPLETED": false,
        "EMPHASIS": null
    },
    {
        "SUBJ": "SE",
        "CRS": "3250",
        "CRN": "5106",
        "TITLE": "Survey of Languages",
        "CREDITS": "3",
        "DAYS": "MWF",
        "COMPLETED": false,
        "EMPHASIS": null
    },
    {
        "SUBJ": "SE",
        "CRS": "3520",
        "CRN": "4867",
        "TITLE": "Database Theory",
        "CREDITS": "3",
        "DAYS": "MWF",
        "COMPLETED": false,
        "EMPHASIS": null
    },
    {
        "SUBJ": "SE",
        "CRS": "4620",
        "CRN": "4964",
        "TITLE": "Distributed Internet Application",
        "CREDITS": "3",
        "DAYS": "TR",
        "COMPLETED": false,
        "EMPHASIS": null
    },
    {
        "SUBJ": "SE",
        "CRS": "3630",
        "CRN": "4965",
        "TITLE": "Mobile Application Development",
        "CREDITS": "3",
        "DAYS": "MWF",
        "COMPLETED": false,
        "EMPHASIS": null
    },
    {
        "SUBJ": "SE",
        "CRS": "3820",
        "CRN": "4965",
        "TITLE": "Back-end Web Development",
        "CREDITS": "3",
        "DAYS": "MWF",
        "COMPLETED": false,
        "EMPHASIS": null
    },
    {
        "SUBJ": "SE",
        "CRS": "3820",
        "CRN": "4965",
        "TITLE": "Cloud Application Development",
        "CREDITS": "3",
        "DAYS": "MWF",
        "COMPLETED": false,
        "EMPHASIS": null
    },
    {
        "SUBJ": "SE",
        "CRS": "4230",
        "CRN": "4966",
        "TITLE": "Advanced Algorithms",
        "CREDITS": "3",
        "DAYS": "MWF",
        "COMPLETED": false,
        "EMPHASIS": null
    },
    {
        "SUBJ": "SE",
        "CRS": "4270",
        "CRN": "4966",
        "TITLE": "Software Maintenance Practices",
        "CREDITS": "3",
        "DAYS": "MWF",
        "COMPLETED": false,
        "EMPHASIS": null
    },
    {
        "SUBJ": "SE",
        "CRS": "4340",
        "CRN": "4966",
        "TITLE": "Secure Coding Practices",
        "CREDITS": "3",
        "DAYS": "MWF",
        "COMPLETED": false,
        "EMPHASIS": null
    },
    {
        "SUBJ": "SE",
        "CRS": "4400",
        "CRN": "4967",
        "TITLE": "SE Practicum I",
        "CREDITS": "4",
        "DAYS": "MW",
        "COMPLETED": false,
        "EMPHASIS": null
    },
    {
        "SUBJ": "SE",
        "CRS": "4450",
        "CRN": "5107",
        "TITLE": "SE Practicum II",
        "CREDITS": "4",
        "DAYS": "MW",
        "COMPLETED": false,
        "EMPHASIS": null
    },
    {
        "SUBJ": "SE",
        "CRS": "3840",
        "CRN": "5107",
        "TITLE": "Web Telemetry, Operations, and Reporting",
        "CREDITS": "4",
        "DAYS": "MW",
        "COMPLETED": false,
        "EMPHASIS": "3"
    },
    {
        "SUBJ": "SE",
        "CRS": "4850",
        "CRN": "5107",
        "TITLE": "Advanced Front-end Development",
        "CREDITS": "4",
        "DAYS": "MW",
        "COMPLETED": false,
        "EMPHASIS": "3"
    }
]
}
